to_sentry/config_parser
to_sentry/transmitter
to_sentry/main
to_sentry
