Metadata-Version: 1.0
Name: to-sentry
Version: 0.0.7
Summary: Simple command line driven logging for sentry.
Home-page: https://github.com/adamdeprince/to_sentry
Author: Adam DePrince
Author-email: adeprince@nypublicradio.org
License: BSD
Platform: UNKNOWN
Classifier: Intended Audience :: Developers
Classifier: Intended Audience :: System Administrators
Classifier: Operating System :: OS Independent
Classifier: Topic :: Software Development
